scrapemove/__init__.py
scrapemove/cli.py
scrapemove/models/__init__.py
scrapemove/models/combined_details.py
scrapemove/models/common.py
scrapemove/models/property_details_screen.py
scrapemove/models/results_screen.py
scrapemove/scrapemove.py
scrapemove-0.2.0.dist-info/entry_points.txt
scrapemove-0.2.0.dist-info/LICENSE
scrapemove-0.2.0.dist-info/WHEEL
scrapemove-0.2.0.dist-info/METADATA
scrapemove-0.2.0.dist-info/RECORD
