Metadata-Version: 2.1
Name: scrapemove
Version: 0.2.0
Summary: Top-level package for scrapemove.
Home-page: https://github.com/briggySmalls/scrapemove
License: MIT
Author: Sam Briggs
Author-email: briggySmalls90@gmail.com
Requires-Python: >=3.7,<4
Classifier: Development Status :: 2 - Pre-Alpha
Classifier: Intended Audience :: Developers
Classifier: License :: OSI Approved :: MIT License
Classifier: Natural Language :: English
Classifier: Programming Language :: Python :: 3
Classifier: Programming Language :: Python :: 3.7
Classifier: Programming Language :: Python :: 3.8
Classifier: Programming Language :: Python :: 3.9
Classifier: Programming Language :: Python :: 3.10
Classifier: Programming Language :: Python :: 3.11
Classifier: Programming Language :: Python :: 3
Classifier: Programming Language :: Python :: 3.5
Classifier: Programming Language :: Python :: 3.6
Classifier: Programming Language :: Python :: 3.7
Classifier: Programming Language :: Python :: 3.8
Requires-Dist: beautifulsoup4 (>=4.11.1,<5.0.0)
Requires-Dist: click
Requires-Dist: fake-useragent (>=1.2.1,<2.0.0)
Requires-Dist: inflection (>=0.5.1,<0.6.0)
Requires-Dist: pydantic (>=1.10.2,<2.0.0)
Requires-Dist: ratelimiter (>=1.2.0.post0,<2.0.0)
Requires-Dist: requests (>=2.28.1,<3.0.0)
